ppmac_macro_substitution/__init__.py
ppmac_macro_substitution/__main__.py
ppmac_macro_substitution/_version.py
ppmac_macro_substitution/ppmac_macro_substitution.py
ppmac_macro_substitution-1.0.1.dist-info/LICENSE
ppmac_macro_substitution-1.0.1.dist-info/METADATA
ppmac_macro_substitution-1.0.1.dist-info/WHEEL
ppmac_macro_substitution-1.0.1.dist-info/entry_points.txt
ppmac_macro_substitution-1.0.1.dist-info/top_level.txt
ppmac_macro_substitution-1.0.1.dist-info/RECORD
