Metadata-Version: 2.1
Name: ppmac-macro-substitution
Version: 1.0.1
Summary: A script that substitutes macros in tamplate files.
Author-email: Urszula Neuman <urszula.neuman@diamond.ac.uk>
License:                                  Apache License
Project-URL: GitHub, https://github.com/DiamondLightSource/ppmac-macro-substitution
Classifier: Development Status :: 3 - Alpha
Classifier: License :: OSI Approved :: Apache Software License
Classifier: Programming Language :: Python :: 3.10
Classifier: Programming Language :: Python :: 3.11
Classifier: Programming Language :: Python :: 3.12
Requires-Python: >=3.10
License-File: LICENSE
Provides-Extra: dev
Requires-Dist: copier; extra == "dev"
Requires-Dist: pipdeptree; extra == "dev"
Requires-Dist: pre-commit; extra == "dev"
Requires-Dist: pyright; extra == "dev"
Requires-Dist: pytest; extra == "dev"
Requires-Dist: pytest-cov; extra == "dev"
Requires-Dist: ruff; extra == "dev"
Requires-Dist: tox-direct; extra == "dev"
Requires-Dist: types-mock; extra == "dev"
